breadpi.py
breadpi-1.0.dist-info/LICENSE
breadpi-1.0.dist-info/METADATA
breadpi-1.0.dist-info/WHEEL
breadpi-1.0.dist-info/top_level.txt
breadpi-1.0.dist-info/RECORD
