Metadata-Version: 2.1
Name: breadpi
Version: 1.0
Summary: BreadPi hardware support package
Home-page: https://github.com/sbcshop/BreadPi
Author: SB Components
Author-email: rd@sb-components.co.uk
Maintainer: SB Components
Maintainer-email: suppport@sb-components.co.uk
License: GNU
Download-URL: https://github.com/sbcshop/BreadPi
Platform: UNKNOWN
Classifier: License :: OSI Approved :: GNU Lesser General Public License v3 (LGPLv3)
Classifier: Intended Audience :: Developers
Classifier: Programming Language :: Python :: 3
